src/__init__.py
src/main.py
src/skewness dan kurtosis.py
src/tes.py
statistic_method/__init__.py
statistic_method/main.py
test/__init__.py
test/sample_test.py
statistic_method-0.2.dist-info/METADATA
statistic_method-0.2.dist-info/WHEEL
statistic_method-0.2.dist-info/top_level.txt
statistic_method-0.2.dist-info/RECORD
